croston/__init__.py
croston/croston.py
croston/example.py
croston-0.1.2.4.dist-info/METADATA
croston-0.1.2.4.dist-info/WHEEL
croston-0.1.2.4.dist-info/top_level.txt
croston-0.1.2.4.dist-info/RECORD
