Metadata-Version: 2.1
Name: croston
Version: 0.1.2.4
Summary: croston model for intermittent time series
Home-page: https://github.com/HamidM6/croston
Author: Hamid Mohammadi
Author-email: hmohammadi6545@gmail.com
Classifier: Programming Language :: Python :: 3.7
Classifier: License :: OSI Approved :: GNU General Public License v3 (GPLv3)
Requires-Dist: numpy
Requires-Dist: pandas
Requires-Dist: scipy
